{
  "_note": "Per-fixture weather forecast overlay (display-only; never a model input). Keyed by HOME_AWAY for group fixtures and by M{match_number} for knockout fixtures (whose teams are unknown until the bracket resolves). Generated from the Open-Meteo cache by build-weather-overlay.mjs.",
  "M101": {
    "temp_c": 33.2,
    "feels_like_c": 36.8,
    "condition": "overcast",
    "code": 3,
    "precip_chance_pct": 17,
    "precip_mm": 0,
    "wind_kmh": 11.3,
    "humidity_pct": 42,
    "forecast_for": "2026-07-14T19:00:00Z",
    "retrieved_at": "2026-07-11T13:57:14.692Z",
    "lead_hours": 77,
    "confidence": "medium"
  },
  "M102": {
    "temp_c": 29.7,
    "feels_like_c": 34.9,
    "condition": "moderate drizzle",
    "code": 53,
    "precip_chance_pct": 21,
    "precip_mm": 0.7,
    "wind_kmh": 11.3,
    "humidity_pct": 61,
    "forecast_for": "2026-07-15T19:00:00Z",
    "retrieved_at": "2026-07-11T13:57:14.846Z",
    "lead_hours": 101,
    "confidence": "low"
  }
}
