{
  "_note": "Per-fixture weather forecast overlay (display-only; never a model input). Keyed by HOME_AWAY. Generated from the Open-Meteo cache by build-weather-overlay.mjs.",
  "MEX_RSA": {
    "temp_c": 21.4,
    "feels_like_c": 24.5,
    "condition": "moderate drizzle",
    "code": 53,
    "precip_chance_pct": 72,
    "precip_mm": 0.8,
    "wind_kmh": 4,
    "humidity_pct": 60,
    "forecast_for": "2026-06-11T19:00:00+00:00",
    "retrieved_at": "2026-06-08T05:17:18.334Z",
    "lead_hours": 85.7,
    "confidence": "medium"
  },
  "USA_PAR": {
    "temp_c": 21.6,
    "feels_like_c": 20.3,
    "condition": "clear sky",
    "code": 0,
    "precip_chance_pct": 0,
    "precip_mm": 0,
    "wind_kmh": 20,
    "humidity_pct": 66,
    "forecast_for": "2026-06-13T01:00:00+00:00",
    "retrieved_at": "2026-06-08T05:17:18.636Z",
    "lead_hours": 115.7,
    "confidence": "low"
  },
  "BRA_MAR": {
    "temp_c": 30.5,
    "feels_like_c": 28.5,
    "condition": "clear sky",
    "code": 0,
    "precip_chance_pct": 10,
    "precip_mm": 0,
    "wind_kmh": 11.8,
    "humidity_pct": 26,
    "forecast_for": "2026-06-13T22:00:00+00:00",
    "retrieved_at": "2026-06-08T05:17:18.836Z",
    "lead_hours": 136.7,
    "confidence": "low"
  },
  "HAI_SCO": {
    "temp_c": 19.1,
    "feels_like_c": 20.2,
    "condition": "clear sky",
    "code": 0,
    "precip_chance_pct": 7,
    "precip_mm": 0,
    "wind_kmh": 5.5,
    "humidity_pct": 80,
    "forecast_for": "2026-06-14T01:00:00+00:00",
    "retrieved_at": "2026-06-08T05:17:18.935Z",
    "lead_hours": 139.7,
    "confidence": "low"
  },
  "SUI_QAT": {
    "temp_c": 32.6,
    "feels_like_c": 33.1,
    "condition": "clear sky",
    "code": 0,
    "precip_chance_pct": 0,
    "precip_mm": 0,
    "wind_kmh": 4.1,
    "humidity_pct": 17,
    "forecast_for": "2026-06-13T19:00:00+00:00",
    "retrieved_at": "2026-06-08T05:17:18.737Z",
    "lead_hours": 133.7,
    "confidence": "low"
  },
  "GER_CUW": {
    "temp_c": 32,
    "feels_like_c": 36.3,
    "condition": "light drizzle",
    "code": 51,
    "precip_chance_pct": 11,
    "precip_mm": 0.1,
    "wind_kmh": 15.3,
    "humidity_pct": 59,
    "forecast_for": "2026-06-14T17:00:00+00:00",
    "retrieved_at": "2026-06-08T05:17:19.136Z",
    "lead_hours": 155.7,
    "confidence": "low"
  },
  "CIV_ECU": {
    "temp_c": 22.7,
    "feels_like_c": 25.6,
    "condition": "light drizzle",
    "code": 51,
    "precip_chance_pct": 21,
    "precip_mm": 0.1,
    "wind_kmh": 10.1,
    "humidity_pct": 90,
    "forecast_for": "2026-06-14T23:00:00+00:00",
    "retrieved_at": "2026-06-08T05:17:19.335Z",
    "lead_hours": 161.7,
    "confidence": "low"
  },
  "NED_JPN": {
    "temp_c": 35.5,
    "feels_like_c": 38.8,
    "condition": "clear sky",
    "code": 0,
    "precip_chance_pct": 17,
    "precip_mm": 0,
    "wind_kmh": 11.9,
    "humidity_pct": 35,
    "forecast_for": "2026-06-14T20:00:00+00:00",
    "retrieved_at": "2026-06-08T05:17:19.236Z",
    "lead_hours": 158.7,
    "confidence": "low"
  },
  "KOR_CZE": {
    "temp_c": 20.2,
    "feels_like_c": 21.6,
    "condition": "dense drizzle",
    "code": 55,
    "precip_chance_pct": 74,
    "precip_mm": 1.1,
    "wind_kmh": 9.4,
    "humidity_pct": 85,
    "forecast_for": "2026-06-12T02:00:00+00:00",
    "retrieved_at": "2026-06-08T05:17:18.436Z",
    "lead_hours": 92.7,
    "confidence": "medium"
  },
  "CAN_BIH": {
    "temp_c": 27.1,
    "feels_like_c": 28.7,
    "condition": "clear sky",
    "code": 0,
    "precip_chance_pct": 16,
    "precip_mm": 0,
    "wind_kmh": 22.8,
    "humidity_pct": 63,
    "forecast_for": "2026-06-12T19:00:00+00:00",
    "retrieved_at": "2026-06-08T05:17:18.536Z",
    "lead_hours": 109.7,
    "confidence": "low"
  },
  "AUS_TUR": {
    "temp_c": 20.8,
    "feels_like_c": 19.3,
    "condition": "overcast",
    "code": 3,
    "precip_chance_pct": 0,
    "precip_mm": 0,
    "wind_kmh": 9,
    "humidity_pct": 48,
    "forecast_for": "2026-06-14T04:00:00+00:00",
    "retrieved_at": "2026-06-08T05:17:19.035Z",
    "lead_hours": 142.7,
    "confidence": "low"
  },
  "SWE_TUN": {
    "temp_c": 29.3,
    "feels_like_c": 31.3,
    "condition": "overcast",
    "code": 3,
    "precip_chance_pct": 22,
    "precip_mm": 0,
    "wind_kmh": 14.8,
    "humidity_pct": 59,
    "forecast_for": "2026-06-15T02:00:00+00:00",
    "retrieved_at": "2026-06-08T05:17:19.435Z",
    "lead_hours": 164.7,
    "confidence": "low"
  }
}
