{
  "_note": "Per-fixture weather forecast overlay (display-only; never a model input). Keyed by HOME_AWAY for group fixtures and by M{match_number} for knockout fixtures (whose teams are unknown until the bracket resolves). Generated from the Open-Meteo cache by build-weather-overlay.mjs.",
  "CPV_KSA": {
    "temp_c": 31,
    "feels_like_c": 33,
    "condition": "mainly clear",
    "code": 1,
    "precip_chance_pct": 1,
    "precip_mm": 0,
    "wind_kmh": 20.6,
    "humidity_pct": 59,
    "forecast_for": "2026-06-27T00:00:00+00:00",
    "retrieved_at": "2026-06-26T09:53:38.370Z",
    "lead_hours": 14.1,
    "confidence": "high"
  },
  "EGY_IRN": {
    "temp_c": 15.8,
    "feels_like_c": 13.1,
    "condition": "clear sky",
    "code": 0,
    "precip_chance_pct": 14,
    "precip_mm": 0,
    "wind_kmh": 21,
    "humidity_pct": 74,
    "forecast_for": "2026-06-27T03:00:00+00:00",
    "retrieved_at": "2026-06-26T09:53:38.466Z",
    "lead_hours": 17.1,
    "confidence": "high"
  },
  "NZL_BEL": {
    "temp_c": 15.7,
    "feels_like_c": 15.1,
    "condition": "overcast",
    "code": 3,
    "precip_chance_pct": 18,
    "precip_mm": 0,
    "wind_kmh": 9.4,
    "humidity_pct": 81,
    "forecast_for": "2026-06-27T03:00:00+00:00",
    "retrieved_at": "2026-06-26T09:53:38.563Z",
    "lead_hours": 17.1,
    "confidence": "high"
  },
  "NOR_FRA": {
    "temp_c": 24.5,
    "feels_like_c": 28.3,
    "condition": "clear sky",
    "code": 0,
    "precip_chance_pct": 5,
    "precip_mm": 0,
    "wind_kmh": 10.1,
    "humidity_pct": 73,
    "forecast_for": "2026-06-26T19:00:00+00:00",
    "retrieved_at": "2026-06-26T09:53:38.177Z",
    "lead_hours": 9.1,
    "confidence": "high"
  },
  "URU_ESP": {
    "temp_c": 18.9,
    "feels_like_c": 19.2,
    "condition": "thunderstorm",
    "code": 95,
    "precip_chance_pct": 98,
    "precip_mm": 1.2,
    "wind_kmh": 13.1,
    "humidity_pct": 85,
    "forecast_for": "2026-06-27T00:00:00+00:00",
    "retrieved_at": "2026-06-26T09:53:38.274Z",
    "lead_hours": 14.1,
    "confidence": "high"
  },
  "ALG_AUT": {
    "temp_c": 26.9,
    "feels_like_c": 30.6,
    "condition": "thunderstorm",
    "code": 95,
    "precip_chance_pct": 7,
    "precip_mm": 0,
    "wind_kmh": 13.6,
    "humidity_pct": 81,
    "forecast_for": "2026-06-28T02:00:00+00:00",
    "retrieved_at": "2026-06-26T09:53:39.046Z",
    "lead_hours": 40.1,
    "confidence": "high"
  },
  "COL_POR": {
    "temp_c": 29.6,
    "feels_like_c": 33.7,
    "condition": "thunderstorm",
    "code": 95,
    "precip_chance_pct": 15,
    "precip_mm": 0,
    "wind_kmh": 11,
    "humidity_pct": 69,
    "forecast_for": "2026-06-27T23:30:00+00:00",
    "retrieved_at": "2026-06-26T09:53:38.854Z",
    "lead_hours": 37.6,
    "confidence": "high"
  },
  "CRO_GHA": {
    "temp_c": 25.4,
    "feels_like_c": 27.2,
    "condition": "light drizzle",
    "code": 51,
    "precip_chance_pct": 38,
    "precip_mm": 0.4,
    "wind_kmh": 6.5,
    "humidity_pct": 62,
    "forecast_for": "2026-06-27T21:00:00+00:00",
    "retrieved_at": "2026-06-26T09:53:38.660Z",
    "lead_hours": 35.1,
    "confidence": "high"
  },
  "JOR_ARG": {
    "temp_c": 30.1,
    "feels_like_c": 30.6,
    "condition": "clear sky",
    "code": 0,
    "precip_chance_pct": 0,
    "precip_mm": 0,
    "wind_kmh": 23.4,
    "humidity_pct": 55,
    "forecast_for": "2026-06-28T02:00:00+00:00",
    "retrieved_at": "2026-06-26T09:53:39.142Z",
    "lead_hours": 40.1,
    "confidence": "high"
  },
  "PAN_ENG": {
    "temp_c": 23.9,
    "feels_like_c": 25.9,
    "condition": "overcast",
    "code": 3,
    "precip_chance_pct": 17,
    "precip_mm": 0,
    "wind_kmh": 5,
    "humidity_pct": 68,
    "forecast_for": "2026-06-27T21:00:00+00:00",
    "retrieved_at": "2026-06-26T09:53:38.757Z",
    "lead_hours": 35.1,
    "confidence": "high"
  },
  "COD_UZB": {
    "temp_c": 31.6,
    "feels_like_c": 31.4,
    "condition": "mainly clear",
    "code": 1,
    "precip_chance_pct": 18,
    "precip_mm": 0,
    "wind_kmh": 20.1,
    "humidity_pct": 43,
    "forecast_for": "2026-06-27T23:30:00+00:00",
    "retrieved_at": "2026-06-26T09:53:38.950Z",
    "lead_hours": 37.6,
    "confidence": "high"
  },
  "SEN_IRQ": {
    "temp_c": 17.3,
    "feels_like_c": 18.2,
    "condition": "overcast",
    "code": 3,
    "precip_chance_pct": 1,
    "precip_mm": 0,
    "wind_kmh": 4.6,
    "humidity_pct": 86,
    "forecast_for": "2026-06-26T19:00:00+00:00",
    "retrieved_at": "2026-06-26T09:53:38.078Z",
    "lead_hours": 9.1,
    "confidence": "high"
  },
  "M73": {
    "temp_c": 20.7,
    "feels_like_c": 20.7,
    "condition": "clear sky",
    "code": 0,
    "precip_chance_pct": 0,
    "precip_mm": 0,
    "wind_kmh": 16.4,
    "humidity_pct": 52,
    "forecast_for": "2026-06-28T19:00:00Z",
    "retrieved_at": "2026-06-26T09:53:39.238Z",
    "lead_hours": 57.1,
    "confidence": "medium"
  },
  "M74": {
    "temp_c": 28.9,
    "feels_like_c": 28.9,
    "condition": "clear sky",
    "code": 0,
    "precip_chance_pct": 4,
    "precip_mm": 0,
    "wind_kmh": 12.8,
    "humidity_pct": 35,
    "forecast_for": "2026-06-29T20:30:00Z",
    "retrieved_at": "2026-06-26T09:53:39.334Z",
    "lead_hours": 82.6,
    "confidence": "medium"
  },
  "M75": {
    "temp_c": 32.8,
    "feels_like_c": 31,
    "condition": "overcast",
    "code": 3,
    "precip_chance_pct": 1,
    "precip_mm": 0,
    "wind_kmh": 27.5,
    "humidity_pct": 38,
    "forecast_for": "2026-06-30T01:00:00Z",
    "retrieved_at": "2026-06-26T09:53:39.430Z",
    "lead_hours": 87.1,
    "confidence": "medium"
  },
  "M76": {
    "temp_c": 33.9,
    "feels_like_c": 38.3,
    "condition": "thunderstorm",
    "code": 95,
    "precip_chance_pct": 0,
    "precip_mm": 0,
    "wind_kmh": 13,
    "humidity_pct": 48,
    "forecast_for": "2026-06-29T17:00:00Z",
    "retrieved_at": "2026-06-26T09:53:39.526Z",
    "lead_hours": 79.1,
    "confidence": "medium"
  },
  "M77": {
    "temp_c": 28,
    "feels_like_c": 30.4,
    "condition": "light drizzle",
    "code": 51,
    "precip_chance_pct": 8,
    "precip_mm": 0.1,
    "wind_kmh": 11,
    "humidity_pct": 63,
    "forecast_for": "2026-06-30T21:00:00Z",
    "retrieved_at": "2026-06-26T09:53:39.622Z",
    "lead_hours": 107.1,
    "confidence": "low"
  },
  "M78": {
    "temp_c": 33,
    "feels_like_c": 35.1,
    "condition": "clear sky",
    "code": 0,
    "precip_chance_pct": 0,
    "precip_mm": 0,
    "wind_kmh": 15.9,
    "humidity_pct": 41,
    "forecast_for": "2026-06-30T17:00:00Z",
    "retrieved_at": "2026-06-26T09:53:39.718Z",
    "lead_hours": 103.1,
    "confidence": "low"
  },
  "M79": {
    "temp_c": 16.8,
    "feels_like_c": 17.3,
    "condition": "light drizzle",
    "code": 51,
    "precip_chance_pct": 82,
    "precip_mm": 0.2,
    "wind_kmh": 3.3,
    "humidity_pct": 80,
    "forecast_for": "2026-07-01T01:00:00Z",
    "retrieved_at": "2026-06-26T09:53:39.814Z",
    "lead_hours": 111.1,
    "confidence": "low"
  },
  "M80": {
    "temp_c": 35.8,
    "feels_like_c": 40.6,
    "condition": "clear sky",
    "code": 0,
    "precip_chance_pct": 1,
    "precip_mm": 0,
    "wind_kmh": 1.8,
    "humidity_pct": 37,
    "forecast_for": "2026-07-01T16:00:00Z",
    "retrieved_at": "2026-06-26T09:53:39.910Z",
    "lead_hours": 126.1,
    "confidence": "low"
  },
  "M81": {
    "temp_c": 24.1,
    "feels_like_c": 21.4,
    "condition": "clear sky",
    "code": 0,
    "precip_chance_pct": 0,
    "precip_mm": 0,
    "wind_kmh": 19.3,
    "humidity_pct": 33,
    "forecast_for": "2026-07-02T00:00:00Z",
    "retrieved_at": "2026-06-26T09:53:40.006Z",
    "lead_hours": 134.1,
    "confidence": "low"
  },
  "M82": {
    "temp_c": 18.7,
    "feels_like_c": 16.1,
    "condition": "overcast",
    "code": 3,
    "precip_chance_pct": 4,
    "precip_mm": 0,
    "wind_kmh": 15,
    "humidity_pct": 51,
    "forecast_for": "2026-07-01T20:00:00Z",
    "retrieved_at": "2026-06-26T09:53:40.102Z",
    "lead_hours": 130.1,
    "confidence": "low"
  },
  "M83": {
    "temp_c": 32.6,
    "feels_like_c": 37.2,
    "condition": "thunderstorm with slight hail",
    "code": 96,
    "precip_chance_pct": 21,
    "precip_mm": 0.2,
    "wind_kmh": 7.2,
    "humidity_pct": 58,
    "forecast_for": "2026-07-02T23:00:00Z",
    "retrieved_at": "2026-06-26T09:53:40.198Z",
    "lead_hours": 157.1,
    "confidence": "low"
  },
  "M84": {
    "temp_c": 21.3,
    "feels_like_c": 22,
    "condition": "clear sky",
    "code": 0,
    "precip_chance_pct": 0,
    "precip_mm": 0,
    "wind_kmh": 14,
    "humidity_pct": 55,
    "forecast_for": "2026-07-02T19:00:00Z",
    "retrieved_at": "2026-06-26T09:53:40.294Z",
    "lead_hours": 153.1,
    "confidence": "low"
  },
  "M85": {
    "temp_c": 14.3,
    "feels_like_c": 12.2,
    "condition": "overcast",
    "code": 3,
    "precip_chance_pct": 27,
    "precip_mm": 0,
    "wind_kmh": 11.1,
    "humidity_pct": 67,
    "forecast_for": "2026-07-03T03:00:00Z",
    "retrieved_at": "2026-06-26T09:53:40.390Z",
    "lead_hours": 161.1,
    "confidence": "low"
  }
}
